rpc4django/__init__.py
rpc4django/jsonrpcdispatcher.py
rpc4django/models.py
rpc4django/rpcdispatcher.py
rpc4django/utils.py
rpc4django/version.py
rpc4django/views.py
rpc4django/xmlrpcdispatcher.py
rpc4django/templates/rpc4django/rpcmethod_summary.html
rpc4django/templatetags/__init__.py
rpc4django/templatetags/rpctags.py
rpc4django-0.6.3.dist-info/LICENSE.rst
rpc4django-0.6.3.dist-info/METADATA
rpc4django-0.6.3.dist-info/WHEEL
rpc4django-0.6.3.dist-info/top_level.txt
rpc4django-0.6.3.dist-info/RECORD
