Metadata-Version: 2.1
Name: rpc4django
Version: 0.6.3
Summary: Handles JSONRPC and XMLRPC requests easily with Django
Home-page: https://github.com/rpc4django/rpc4django
Author: David Fischer
Author-email: djfische@gmail.com
License: BSD
Platform: OS Independent
Classifier: Development Status :: 5 - Production/Stable
Classifier: Environment :: Web Environment
Classifier: Framework :: Django
Classifier: Intended Audience :: Developers
Classifier: License :: OSI Approved :: BSD License
Classifier: Operating System :: OS Independent
Classifier: Programming Language :: Python
Classifier: Programming Language :: Python :: 2.7
Classifier: Programming Language :: Python :: 3
Classifier: Programming Language :: Python :: 3.4
Classifier: Programming Language :: Python :: 3.5
Classifier: Programming Language :: Python :: 3.6
Classifier: Programming Language :: Python :: 3.7
Classifier: Programming Language :: Python :: 3.8
Classifier: Topic :: Internet :: WWW/HTTP :: Dynamic Content
Classifier: Topic :: Software Development :: Libraries :: Python Modules
Requires-Dist: Django (>=1.9)
Requires-Dist: defusedxml
Provides-Extra: rest
Requires-Dist: docutils (>=0.4) ; extra == 'rest'
